LICENSE
README.md
setup.py
CinetPay.egg-info/PKG-INFO
CinetPay.egg-info/SOURCES.txt
CinetPay.egg-info/dependency_links.txt
CinetPay.egg-info/requires.txt
CinetPay.egg-info/top_level.txt
cinetpay/__init__.py
cinetpay/_client.py
cinetpay/_schema.py
cinetpay/_services.py
cinetpay/_types.py
cinetpay/_utils.py