Metadata-Version: 2.1
Name: CinetPay
Version: 0.0.1
Summary: Python SDK for CinetPay Payment API. 
Home-page: https://github.com/AllDotPy/CinetPay.git
Author: #Einswilli
Author-email: einswilligoeh@email.com
License-File: LICENSE
Requires-Dist: httpx
Requires-Dist: simplejson
Requires-Dist: colorlog
Requires-Dist: pydantic
